sqss/__init__.py
sqss/__main__.py
sqss/core/__init__.py
sqss/core/compiler.py
sqss/core/macro/__init__.py
sqss/core/macro/abs_macro.py
sqss/core/macro/include.py
sqss/core/macro/mixin.py
sqss/core/morpheme.py
sqss/core/property/__init__.py
sqss/core/scope.py
sqss/core/selector/__init__.py
sqss/core/selector/attr_sel.py
sqss/core/selector/pseudo_class.py
sqss/core/selector/rule.py
sqss/core/selector/sub_control.py
sqss/core/variable/__init__.py
sqss/core/variable/fun.py
sqss/core/variable/num.py
sqss/core/variable/str.py
sqss/core/variable/var.py
sqss/exception/__init__.py
sqss/exception/CompileException.py
sqss/exception/ValAssignedSetException.py
sqss/util/__init__.py
sqss/util/cli/__init__.py
sqss/util/cli/command.py
sqss/util/string_util.py
sqss-0.1.3.dist-info/entry_points.txt
sqss-0.1.3.dist-info/WHEEL
sqss-0.1.3.dist-info/METADATA
sqss-0.1.3.dist-info/RECORD
